resqlconnection/__init__.py
resqlconnection/example_of_use.py
resqlconnection/methods.py
resqlconnection/sql_connection.py
resqlconnection-1.2.dist-info/METADATA
resqlconnection-1.2.dist-info/WHEEL
resqlconnection-1.2.dist-info/top_level.txt
resqlconnection-1.2.dist-info/RECORD
