Metadata-Version: 2.1
Name: resqlconnection
Version: 1.2
Summary: The RE crawling tool
Author: Andreas Rystad, Alex Hodgson, Wilfred Husemoen
Author-email: TechnologySupport@rystadenergy.com
License: MIT
Requires-Dist: pandas (>1.3.0)
Requires-Dist: numpy (>1.21.0)
Requires-Dist: SQLAlchemy (>1.4.20)
Requires-Dist: pyodbc (>4.0.30)
Requires-Dist: pymssql (>2.2.1)
Requires-Dist: setuptools (>56.0.0)
